pythonase/__init__.py
pythonase/_version.py
pythonase/io.py
pythonase/print_functions.py
pythonase/region.py
pythonase/run.py
pythonase/file_parser_mem/__init__.py
pythonase/file_parser_mem/bed.py
pythonase/file_parser_mem/gtf.py
pythonase/file_parser_mem/vcf.py
pythonase/types/__init__.py
pythonase/types/cli.py
pythonase-0.1.7.dist-info/METADATA
pythonase-0.1.7.dist-info/WHEEL
pythonase-0.1.7.dist-info/top_level.txt
pythonase-0.1.7.dist-info/RECORD
