Metadata-Version: 2.1
Name: pythonase
Version: 0.1.7
Summary: Pythonase is a collection of gist functions (mainly for bioinformatic analysis) for saving time.
Home-page: 
Author: Li Yao
Author-email: py_packages@yaobio.com
Requires-Dist: numpy
Requires-Dist: pandas
Requires-Dist: matplotlib
Requires-Dist: scipy
